README.md
setup.cfg
setup.py
matrix_factorization/__init__.py
matrix_factorization/baseline_model.py
matrix_factorization/kernel_matrix_factorization.py
matrix_factorization/kernels.py
matrix_factorization/recommender_base.py
matrix_factorization/utils.py
matrix_factorization.egg-info/PKG-INFO
matrix_factorization.egg-info/SOURCES.txt
matrix_factorization.egg-info/dependency_links.txt
matrix_factorization.egg-info/requires.txt
matrix_factorization.egg-info/top_level.txt