Metadata-Version: 2.1
Name: matrix-factorization
Version: 1.3
Summary: Library for matrix factorization for recommender systems using collaborative filtering
Home-page: https://github.com/Quang-Vinh/matrix-factorization
Author: Quang-Vinh Do
Author-email: qdo086@uottawa.ca
License: MIT
Download-URL: https://github.com/Quang-Vinh/matrix-factorization/archive/v1.3.tar.gz
Platform: UNKNOWN
Classifier: Programming Language :: Python :: 3
Classifier: Operating System :: OS Independent
Classifier: License :: OSI Approved :: MIT License
Requires-Python: >=3.6
